arasents/__init__.py
arasents/arasents.py
arasents/emos.db
arasents/stop_words.txt
arasents-0.0b0.dist-info/METADATA
arasents-0.0b0.dist-info/RECORD
arasents-0.0b0.dist-info/WHEEL
arasents-0.0b0.dist-info/top_level.txt
