Metadata-Version: 2.1
Name: arasents
Version: 0.0b0
Summary: A small package for sentiments analysis
Home-page: UNKNOWN
Author: muhamed hachoum
Author-email: arab@muslim.com
License: UNKNOWN
Platform: UNKNOWN
Classifier: Programming Language :: Python :: 3
Classifier: License :: OSI Approved :: MIT License
Classifier: Operating System :: OS Independent
